ai_logstash/__init__.py
ai_logstash/error_handler.py
ai_logstash/logger.py
ai_logstash/version.py
ai_logstash-0.7.0.dist-info/METADATA
ai_logstash-0.7.0.dist-info/WHEEL
ai_logstash-0.7.0.dist-info/top_level.txt
ai_logstash-0.7.0.dist-info/RECORD
