Metadata-Version: 2.1
Name: ai_logstash
Version: 0.7.0
Summary: A versatile logging package with async support
Author: Bip Bop
Author-email: no_email@example.com
Classifier: Development Status :: 3 - Alpha
Classifier: Intended Audience :: Developers
Classifier: License :: OSI Approved :: MIT License
Classifier: Programming Language :: Python :: 3
Classifier: Programming Language :: Python :: 3.11
Requires-Dist: python-logstash-async
Provides-Extra: test
Requires-Dist: hypothesis; extra == "test"
Requires-Dist: ruff; extra == "test"
Requires-Dist: pyproj; extra == "test"
Requires-Dist: pytest; extra == "test"
Requires-Dist: pytest-cov; extra == "test"
Requires-Dist: pytest-asyncio; extra == "test"
Requires-Dist: tox; extra == "test"
Requires-Dist: build; extra == "test"
Requires-Dist: pip-audit; extra == "test"
Requires-Dist: twine; extra == "test"
